vimgolf_gym/__init__.py
vimgolf_gym/_vimrc.py
vimgolf_gym/dataclasses.py
vimgolf_gym/lib.py
vimgolf_gym/log_parser.py
vimgolf_gym/terminal_executor.py
vimgolf_gym/vimgolf.py
vimgolf_gym-0.1.1.dist-info/LICENSE
vimgolf_gym-0.1.1.dist-info/METADATA
vimgolf_gym-0.1.1.dist-info/WHEEL
vimgolf_gym-0.1.1.dist-info/top_level.txt
vimgolf_gym-0.1.1.dist-info/RECORD
