Metadata-Version: 2.1
Name: vimgolf-gym
Version: 0.1.1
Summary: A gym environment for VimGolf challenges
Home-page: https://github.com/james4ever0/vimgolf-gym
Author: James Brown
Author-email: randomvoidmail@foxmail.com
Classifier: Programming Language :: Python :: 3
Classifier: Operating System :: OS Independent
Requires-Python: >=3.8
License-File: LICENSE
Requires-Dist: vimgolf (==0.5.1)
Requires-Dist: agg-python-bindings (==0.1.4)
Requires-Dist: ptyprocess (==0.7.0)
Requires-Dist: pillow
Requires-Dist: pydantic
Requires-Dist: parse (==1.20.2)
Requires-Dist: requests (==2.31.0)
